neurogym/__init__.py
neurogym/core.py
neurogym/config/__init__.py
neurogym/config/base.py
neurogym/config/config.py
neurogym/config/components/__init__.py
neurogym/config/components/agent.py
neurogym/config/components/env.py
neurogym/config/components/monitor.py
neurogym/envs/__init__.py
neurogym/envs/registration.py
neurogym/envs/collections/__init__.py
neurogym/envs/collections/perceptualdecisionmaking.py
neurogym/envs/collections/priors.py
neurogym/envs/collections/yang19.py
neurogym/envs/contrib/__init__.py
neurogym/envs/contrib/anglereproduction.py
neurogym/envs/contrib/changingenvironment.py
neurogym/envs/contrib/cv_learning.py
neurogym/envs/contrib/ibl.py
neurogym/envs/contrib/leverpress.py
neurogym/envs/contrib/matchingpenny.py
neurogym/envs/contrib/memoryrecall.py
neurogym/envs/contrib/pneumostomeopening.py
neurogym/envs/native/__init__.py
neurogym/envs/native/annubes.py
neurogym/envs/native/antireach.py
neurogym/envs/native/bandit.py
neurogym/envs/native/contextdecisionmaking.py
neurogym/envs/native/dawtwostep.py
neurogym/envs/native/delaycomparison.py
neurogym/envs/native/delaymatchcategory.py
neurogym/envs/native/delaymatchsample.py
neurogym/envs/native/delaypairedassociation.py
neurogym/envs/native/detection.py
neurogym/envs/native/dualdelaymatchsample.py
neurogym/envs/native/economicdecisionmaking.py
neurogym/envs/native/gonogo.py
neurogym/envs/native/hierarchicalreasoning.py
neurogym/envs/native/intervaldiscrimination.py
neurogym/envs/native/multisensory.py
neurogym/envs/native/null.py
neurogym/envs/native/perceptualdecisionmaking.py
neurogym/envs/native/postdecisionwager.py
neurogym/envs/native/probabilisticreasoning.py
neurogym/envs/native/reaching.py
neurogym/envs/native/reachingdelayresponse.py
neurogym/envs/native/readysetgo.py
neurogym/envs/native/spatialsuppressmotion.py
neurogym/envs/native/tonedetection.py
neurogym/envs/psychopy/__init__.py
neurogym/envs/psychopy/perceptualdecisionmaking.py
neurogym/envs/psychopy/psychopy_env.py
neurogym-2.2.0.dist-info/licenses/LICENSE
neurogym-2.2.0.dist-info/licenses/NOTICE
neurogym-2.2.0.dist-info/METADATA
neurogym-2.2.0.dist-info/WHEEL
neurogym-2.2.0.dist-info/top_level.txt
neurogym-2.2.0.dist-info/RECORD
