Metadata-Version: 2.4
Name: neurogym
Version: 2.2.0
Summary: NeuroGym: Gymnasium-style Cognitive Neuroscience Tasks
Author-email: Giulia Crocioni <g.crocioni@esciencecenter.nl>, Dani Bodor <d.bodor@esciencecenter.nl>, Nathan Cloos <cloosnathan@gmail.com>, Alexander Hadjiivanov <a.hadjiivanov@esciencecenter.nl>, Guangyu Robert Yang <gyyang.neuro@gmail.com>, Jorge Mejias <j.f.mejias@uva.nl>, Manuel Molano Mazon <manuelmolanomazon@gmail.com>
License: Apache-2.0 License
Project-URL: Repository, https://github.com/neurogym/neurogym
Project-URL: Issues, https://github.com/neurogym/neurogym
Project-URL: Documentation, https://neurogym.github.io/neurogym
Project-URL: Changelog, https://github.com/neurogym/neurogym/CHANGELOG.md
Keywords: neuroscience,neural networks,supervised learning,reinforcement learning,synthetic data
Classifier: License :: OSI Approved :: Apache Software License
Classifier: Natural Language :: English
Classifier: Programming Language :: Python :: 3.10
Classifier: Programming Language :: Python :: 3.11
Classifier: Programming Language :: Python :: 3.12
Requires-Python: >=3.10
License-File: LICENSE
License-File: NOTICE
Requires-Dist: pydantic-settings
Requires-Dist: loguru
Requires-Dist: tqdm
Requires-Dist: tomlkit
Requires-Dist: numpy==2.1.*
Requires-Dist: gymnasium==0.29.*
Requires-Dist: matplotlib==3.9.*
Requires-Dist: scipy==1.14.*
Provides-Extra: dev
Requires-Dist: pytest; extra == "dev"
Requires-Dist: pytest-cov; extra == "dev"
Requires-Dist: coverage[toml]; extra == "dev"
Requires-Dist: ruff==0.11.*; extra == "dev"
Requires-Dist: mypy; extra == "dev"
Requires-Dist: types-docutils; extra == "dev"
Requires-Dist: scipy-stubs; extra == "dev"
Requires-Dist: mkdocs; extra == "dev"
Requires-Dist: mkdocs-material; extra == "dev"
Requires-Dist: mkdocs-exclude; extra == "dev"
Requires-Dist: mkdocs-redirects; extra == "dev"
Requires-Dist: mkdocstrings-python; extra == "dev"
Requires-Dist: mike; extra == "dev"
Requires-Dist: mkdocs-jupyter; extra == "dev"
Requires-Dist: black; extra == "dev"
Requires-Dist: bump-my-version; extra == "dev"
Provides-Extra: publishing
Requires-Dist: build; extra == "publishing"
Requires-Dist: twine; extra == "publishing"
Requires-Dist: wheel; extra == "publishing"
Provides-Extra: rl
Requires-Dist: stable-baselines3>=2.3.2; extra == "rl"
Requires-Dist: sb3-contrib; extra == "rl"
Provides-Extra: notebooks
Requires-Dist: nbmake; extra == "notebooks"
Requires-Dist: tensorflow; extra == "notebooks"
Dynamic: license-file
